{
    "min_g_struct_elems": [
        10
    ],
    "freq_dict": {
        "11": 2774,
        "12": 2742,
        "10": 2720,
        "9": 2592,
        "13": 2592,
        "8": 2420,
        "7": 2390,
        "6": 2376,
        "5": 2354,
        "14": 2336,
        "4": 2294,
        "3": 2160,
        "15": 1992,
        "2": 1910,
        "16": 1584,
        "1": 1496,
        "17": 1142,
        "0": 866,
        "18": 702,
        "19": 306
    },
    "highest_freq": [
        [
            11,
            2774
        ],
        [
            12,
            2742
        ],
        [
            10,
            2720
        ],
        [
            9,
            2592
        ],
        [
            13,
            2592
        ],
        [
            8,
            2420
        ],
        [
            7,
            2390
        ],
        [
            6,
            2376
        ],
        [
            5,
            2354
        ],
        [
            14,
            2336
        ]
    ],
    "res_freq_elec1": {
        "58": 10,
        "59": 4,
        "13": 2
    },
    "res_freq_elec2": {
        "58": 10,
        "13": 2,
        "59": 4
    }
}